{
  "users": [
    {
      "id": 1
    },
    {
      "name": "Marito",
      "age": 14,
      "id": 2
    },
    {
      "name": "Marito",
      "age": 14,
      "id": 3
    },
    {
      "name": "Marito",
      "age": 14,
      "id": 4
    },
    {
      "name": "Marito",
      "age": 14,
      "id": 5
    },
    {
      "name": "Marito",
      "age": 14,
      "id": 6
    },
    {
      "name": "Marito",
      "age": 14,
      "id": 7
    },
    {
      "name": "Marito",
      "age": 14,
      "id": 8
    },
    {
      "name": "Marito",
      "age": 14,
      "id": 9
    },
    {
      "name": "Marito",
      "age": 14,
      "id": 10
    },
    {
      "name": "Marito",
      "age": 14,
      "id": 11
    },
    {
      "name": "Marito",
      "age": 14,
      "id": 12
    },
    {
      "name": "Marito",
      "age": 14,
      "id": 13
    },
    {
      "name": "Marito",
      "age": 14,
      "id": 14
    },
    {
      "name": "Marito",
      "age": 14,
      "id": 15
    },
    {
      "name": "Marito",
      "age": 14,
      "id": 16
    },
    {
      "name": "Marito",
      "age": 14,
      "id": 17
    },
    {
      "name": "Marito",
      "age": 14,
      "id": 18
    },
    {
      "name": "Nolito",
      "age": 50,
      "id": 19
    },
    {
      "name": "Nolito",
      "age": 50,
      "id": 20
    },
    {
      "name": "Nolito",
      "age": 50,
      "id": 21
    },
    {
      "name": "Nolito",
      "age": 50,
      "id": 22
    },
    {
      "name": "Nolito",
      "age": 50,
      "id": 23
    },
    {
      "name": "Nolito",
      "age": 50,
      "id": 24
    },
    {
      "name": "Nolito",
      "age": 50,
      "id": 25
    },
    {
      "name": "Nolito",
      "age": 50,
      "id": 26
    },
    {
      "name": "Nolito",
      "age": 50,
      "id": 27
    },
    {
      "name": "New won",
      "age": 44,
      "id": 28
    },
    {
      "name": "Nolito",
      "age": 50,
      "id": 29
    },
    {
      "name": "New won",
      "age": 44,
      "id": 30
    },
    {
      "name": "Nolito",
      "age": 50,
      "id": 31
    },
    {
      "name": "New won",
      "age": 44,
      "id": 32
    },
    {
      "name": "Nolito",
      "age": 50,
      "id": 33
    },
    {
      "name": "New won",
      "age": 44,
      "id": 34
    },
    {
      "name": "Nolito",
      "age": 50,
      "id": 35
    },
    {
      "name": "New won",
      "age": 44,
      "id": 36
    },
    {
      "name": "Nolito",
      "age": 50,
      "id": 37
    },
    {
      "name": "New won",
      "age": 44,
      "id": 38
    },
    {
      "name": "Nolito",
      "age": 50,
      "id": 39
    },
    {
      "name": "Nolito",
      "age": 50,
      "id": 40
    },
    {
      "name": "Nolito",
      "age": 50,
      "id": 41
    },
    {
      "name": "Nolito",
      "age": 50,
      "id": 42
    },
    {
      "name": "Nolito",
      "age": 50,
      "id": 43
    },
    {
      "name": "Nolito",
      "age": 50,
      "id": 44
    },
    {
      "name": "Nolito",
      "age": 50,
      "id": 45
    },
    {
      "name": "Nolito",
      "age": 50,
      "id": 46
    },
    {
      "name": "Nolito",
      "age": 50,
      "id": 47
    },
    {
      "name": "Nolito",
      "age": 50,
      "id": 48
    },
    {
      "name": "Nolito",
      "age": 50,
      "id": 49
    },
    {
      "name": "Nolito",
      "age": 50,
      "id": 50
    },
    {
      "name": "Nolito",
      "age": 50,
      "id": 51
    },
    {
      "name": "Nolito",
      "age": 50,
      "id": 52
    },
    {
      "name": "Perensejo",
      "id": 53
    },
    {
      "name": "Perensejo",
      "id": 54
    },
    {
      "name": "Perensejo",
      "id": 55
    },
    {
      "name": "Perensejo",
      "age": 0,
      "id": 56
    },
    {
      "name": "Namen",
      "age": 30,
      "id": 57
    },
    {
      "name": "Pablito",
      "age": 80,
      "id": 58
    },
    {
      "name": "alfreo",
      "age": 83,
      "id": 59
    },
    {
      "name": "Gogo",
      "age": 36,
      "id": 60
    },
    {
      "name": "Hello",
      "age": 68,
      "id": 61
    },
    {
      "name": "Cakis",
      "age": 96,
      "id": 62
    },
    {
      "name": "Cakis",
      "age": 96,
      "id": 63
    },
    {
      "name": "Fulanito",
      "age": 30,
      "id": 64
    },
    {
      "name": "Renzo",
      "age": 29,
      "id": 65
    },
    {
      "name": "Otroman",
      "age": 10,
      "id": 66
    },
    {
      "name": "zaiko",
      "age": 36,
      "id": 67
    },
    {
      "name": "Fulanito",
      "age": 30,
      "id": 68
    },
    {
      "name": "Fran",
      "age": 56,
      "id": 69
    }
  ]
}